pivotcrop/__init__.py
pivotcrop/bbox.py
pivotcrop/cropper.py
pivotcrop/draw.py
pivotcrop/log.py
pivotcrop/types.py
tests/__init__.py
tests/test_crop.py
pivotcrop-0.0.1.dist-info/LICENSE
pivotcrop-0.0.1.dist-info/METADATA
pivotcrop-0.0.1.dist-info/WHEEL
pivotcrop-0.0.1.dist-info/top_level.txt
pivotcrop-0.0.1.dist-info/RECORD
