Metadata-Version: 2.1
Name: pivotcrop
Version: 0.0.1
Summary: Package for cropping directories of images based on a pivot point.
Home-page: https://github.com/Katsutoshii/pivotcrop
Author: Josiah Putman
Project-URL: Source, https://github.com/Katsutoshii/pivotcrop
Classifier: Programming Language :: Python :: 3
Classifier: License :: OSI Approved :: MIT License
Classifier: Operating System :: OS Independent
Requires-Python: >=3.7
License-File: LICENSE
Requires-Dist: attrs (==22.2.0)
Requires-Dist: autopep8
Requires-Dist: certifi (==2022.12.7)
Requires-Dist: chardet (==4.0.0)
Requires-Dist: charset-normalizer (==2.1.1)
Requires-Dist: colorama (==0.4.6)
Requires-Dist: contourpy (==1.0.6)
Requires-Dist: cycler (==0.10.0)
Requires-Dist: exceptiongroup (==1.1.0)
Requires-Dist: fonttools (==4.38.0)
Requires-Dist: idna (==2.10)
Requires-Dist: iniconfig (==2.0.0)
Requires-Dist: kiwisolver (==1.4.4)
Requires-Dist: matplotlib (==3.6.2)
Requires-Dist: numpy (==1.24.1)
Requires-Dist: packaging (==23.0)
Requires-Dist: Pillow (==9.4.0)
Requires-Dist: pluggy (==1.0.0)
Requires-Dist: pycodestyle
Requires-Dist: pyparsing (==2.4.7)
Requires-Dist: pytest (==7.2.1)
Requires-Dist: python-dateutil (==2.8.2)
Requires-Dist: requests (==2.28.1)
Requires-Dist: requests-toolbelt (==0.10.1)
Requires-Dist: toml
Requires-Dist: tomli (==2.0.1)
Requires-Dist: tqdm (==4.64.1)
Requires-Dist: wincertstore (==0.2)
Provides-Extra: dev
Requires-Dist: check-manifest ; extra == 'dev'
Requires-Dist: pytest ; extra == 'dev'
Requires-Dist: pytest-cov ; extra == 'dev'
Requires-Dist: coverage ; extra == 'dev'
Requires-Dist: mkdocs ; extra == 'dev'
Requires-Dist: mkdocstrings[python] ; extra == 'dev'
Requires-Dist: mkdocs-material ; extra == 'dev'
